okdb/__init__.py
okdb/nstore2.py
okdb-0.1.0.dist-info/LICENSE
okdb-0.1.0.dist-info/WHEEL
okdb-0.1.0.dist-info/METADATA
okdb-0.1.0.dist-info/RECORD
