Metadata-Version: 2.1
Name: okdb
Version: 0.1.0
Summary: Simple database with which I am productive
License: MIT
Author: Amirouche
Author-email: amirouche@hyper.dev
Requires-Python: >=3.7,<4.0
Classifier: License :: OSI Approved :: MIT License
Classifier: Programming Language :: Python :: 3
Classifier: Programming Language :: Python :: 3.7
Classifier: Programming Language :: Python :: 3.8
Classifier: Programming Language :: Python :: 3.9
